netkeiber/__init__.py
netkeiber/raceGetter.py
netkeiber/raceGetters.py
netkeiber/Getter/get_RaceData.py
netkeiber/Getter/log_race_id.py
netkeiber/Getter/prm_race_table.py
netkeiber/Getter/prm_traning_ass.py
netkeiber/Getter/trn_horse_result.py
netkeiber/Getter/trn_open_info.py
netkeiber/Getter/trn_race_id.py
netkeiber/Getter/trn_race_result.py
netkeiber/Getter/trn_refund_info.py
netkeiber/Getter/Base/baseGetter.py
netkeiber/Library/netkeiberConfig.py
netkeiber/Library/netkeiberConfiger.py
netkeiber/Library/netkeiberController.py
netkeiber/Library/netkeiberDeclare.py
netkeiber/Library/netkeiberException.py
netkeiber/Library/netkeiberGlobals.py
netkeiber/Library/netkeiberMailer.py
netkeiber/Models/log_race_id.py
netkeiber/Models/mst_horse.py
netkeiber/Models/mst_horse_sign.py
netkeiber/Models/mst_howner.py
netkeiber/Models/mst_jockey.py
netkeiber/Models/mst_peds.py
netkeiber/Models/mst_racecourse.py
netkeiber/Models/mst_trainer.py
netkeiber/Models/prm_odds.py
netkeiber/Models/prm_race_info.py
netkeiber/Models/prm_race_table.py
netkeiber/Models/prm_traning_ass.py
netkeiber/Models/trn_horse_result.py
netkeiber/Models/trn_open_info.py
netkeiber/Models/trn_race_id.py
netkeiber/Models/trn_race_info.py
netkeiber/Models/trn_race_result.py
netkeiber/Models/trn_refund_info.py
netkeiber/Models/viw_raceid_record_count.py
netkeiber/Register/mst_racecourse.py
netkeiber/Register/register_RaceData.py
netkeiber/Register/trn_race_result.py
netkeiber/Register/Base/baseRegister.py
netkeiber-1.0.51.dist-info/METADATA
netkeiber-1.0.51.dist-info/WHEEL
netkeiber-1.0.51.dist-info/top_level.txt
netkeiber-1.0.51.dist-info/RECORD
