Metadata-Version: 2.1
Name: netkeiber
Version: 1.0.51
Summary: netkeiba Package
Home-page: https://github.com/kaioman/netkeiber.git
Author: Unchain Works
Author-email: kajin0318@gmail.com
License: BSD-3-Clause
Keywords: netkeiber
Classifier: Development Status :: 5 - Production/Stable
Classifier: License :: OSI Approved :: BSD License
Classifier: Programming Language :: Python
Classifier: Programming Language :: Python :: 3
Classifier: Programming Language :: Python :: 3.4
Classifier: Programming Language :: Python :: 3.5
Classifier: Programming Language :: Python :: 3.6
Classifier: Programming Language :: Python :: 3.7
Classifier: Programming Language :: Python :: 3.8
Classifier: Programming Language :: Python :: 3.9
Classifier: Topic :: Database
Classifier: Topic :: Software Development :: Libraries :: Python Modules
Requires-Dist: beautifulsoup4 (==4.10.0)
Requires-Dist: bleach (==4.1.0)
Requires-Dist: bs4 (==0.0.1)
Requires-Dist: certifi (==2021.10.8)
Requires-Dist: charset-normalizer (==2.0.9)
Requires-Dist: colorama (==0.4.4)
Requires-Dist: docutils (==0.18.1)
Requires-Dist: et-xmlfile (==1.1.0)
Requires-Dist: greenlet (==1.1.2)
Requires-Dist: idna (==3.3)
Requires-Dist: importlib-metadata (==4.8.2)
Requires-Dist: keyring (==23.4.0)
Requires-Dist: LibHanger
Requires-Dist: lxml (==4.9.1)
Requires-Dist: numpy (==1.21.4)
Requires-Dist: openpyxl (==3.0.10)
Requires-Dist: packaging (==21.3)
Requires-Dist: pandas
Requires-Dist: Pillow (==9.3.0)
Requires-Dist: pkginfo (==1.8.2)
Requires-Dist: psycopg2 (==2.9.5)
Requires-Dist: Pygments (==2.10.0)
Requires-Dist: pyparsing (==3.0.6)
Requires-Dist: python-dateutil (==2.8.2)
Requires-Dist: pytz (==2021.3)
Requires-Dist: pywin32-ctypes (==0.2.0)
Requires-Dist: readme-renderer (==30.0)
Requires-Dist: requests (==2.26.0)
Requires-Dist: requests-toolbelt (==0.9.1)
Requires-Dist: rfc3986 (==1.5.0)
Requires-Dist: Scrapinger
Requires-Dist: selenium (==3.141.0)
Requires-Dist: six (==1.16.0)
Requires-Dist: soupsieve (==2.3.1)
Requires-Dist: SQLAlchemy
Requires-Dist: tqdm (==4.62.3)
Requires-Dist: urllib3 (==1.26.7)
Requires-Dist: webencodings (==0.5.1)
Requires-Dist: zipp (==3.6.0)
